py_eol/__init__.py
py_eol/_eol_data.py
py_eol/checker.py
py_eol/cli.py
py_eol/sync_data.py
py_eol-0.4.0.dist-info/licenses/LICENSE
py_eol-0.4.0.dist-info/METADATA
py_eol-0.4.0.dist-info/WHEEL
py_eol-0.4.0.dist-info/entry_points.txt
py_eol-0.4.0.dist-info/top_level.txt
py_eol-0.4.0.dist-info/RECORD
