Metadata-Version: 2.4
Name: py-eol
Version: 0.4.0
Summary: Check if a Python version is End-Of-Life (EOL)
Author-email: Xianpeng Shen <xianpeng.shen@gmail.com>
License-Expression: MIT
Project-URL: Homepage, https://github.com/shenxianpeng/py-eol
Project-URL: Repository, https://github.com/shenxianpeng/py-eol.git
Project-URL: Issues, https://github.com/shenxianpeng/py-eol/issues
Project-URL: Funding, https://github.com/sponsors/shenxianpeng
Keywords: python,eol,end-of-life
License-File: LICENSE
Requires-Dist: requests
Requires-Dist: PyYAML
Requires-Dist: packaging
Provides-Extra: dev
Requires-Dist: requests; extra == "dev"
Requires-Dist: pytest; extra == "dev"
Dynamic: license-file
